{
  "symbol": "XRP",
  "name": "XRP",
  "chain": "BSC",
  "chainId": 56,
  "address": "0x1D2F0da169ceB9fC7B3144628dB156f3F6c60dBE",
  "decimals": 18,
  "category": "swing",
  "timestamp": "2026-04-19T02:20:26.451Z",
  "timestampUnix": 1776565220005,
  "price": {
    "usd": 1.4292877739059973,
    "idr": 24012.034601620755
  },
  "change": {
    "1h": -0.5,
    "4h": -0.08,
    "24h": -3
  },
  "range24h": {
    "high": 1.4892581309709043,
    "low": 1.4144954618638665
  },
  "market": {
    "volume24h_usd": 1093866.891304077,
    "volume24h_idr": 18376963773.908497,
    "liquidity_usd": 5494324.257357416,
    "liquidity_idr": 92304647523.60458,
    "txs24h": 6048
  },
  "portfolio": {
    "holdings": 1.4302903e-9,
    "entryPrice": 1.455,
    "entryCost_usd": 5.16,
    "entryCost_idr": 86688,
    "currentValue_usd": 2.044296438926341e-9,
    "currentValue_idr": 0.00003434418017396253,
    "pnl_usd": -5.159999997955704,
    "pnl_idr": -86687.99996565582,
    "pnl_pct": -1.77
  },
  "zones": {
    "buyZone": 1.382,
    "sellTarget1": 1.673,
    "sellTarget2": 1.819,
    "sellTarget3": 2.037,
    "stopLoss": 1.339,
    "trailingStop": 1.4459261869178972,
    "trailingStopPct": 6
  },
  "signal": "TRAILING_STOP"
}