{"symbol":"SAPI","name":"SAPI","chain":"BSC","chainId":56,"address":"0x1ae102c0c30d604e7089fb210dd4b42c01287f32","decimals":18,"category":"moonshot","timestamp":"2026-04-22T08:23:32.065Z","timestampUnix":1776846211411,"price":{"usd":0.004811898283654853,"idr":80.83989116540154},"change":{"1h":0.33,"4h":1.7,"24h":1.62},"range24h":{"high":0.004811898283654853,"low":0.0045832226940403994},"market":{"volume24h_usd":21.491007340149736,"volume24h_idr":361048.92331451556,"liquidity_usd":1657.2528777286482,"liquidity_idr":27841848.34584129,"txs24h":36},"portfolio":{"holdings":12169137.99099191,"entryPrice":0.004687,"entryCost_usd":6.63,"entryCost_idr":111384,"currentValue_usd":6.63,"currentValue_idr":111384,"pnl_usd":0,"pnl_idr":0,"pnl_pct":2.66},"zones":{"buyZone":0.004453,"sellTarget1":0.00539,"sellTarget2":0.006093,"sellTarget3":0.007031,"stopLoss":0.004312,"trailingStop":0.004411952557909226,"trailingStopPct":8},"signal":"HOLD"}